example_package_u2176605/__init__.py
example_package_u2176605/example.py
example_package_u2176605-0.0.4.dist-info/LICENSE.txt
example_package_u2176605-0.0.4.dist-info/METADATA
example_package_u2176605-0.0.4.dist-info/WHEEL
example_package_u2176605-0.0.4.dist-info/top_level.txt
example_package_u2176605-0.0.4.dist-info/RECORD
